fishdata/__init__.py
fishdata/data.py
fishdata-1.9.dist-info/METADATA
fishdata-1.9.dist-info/WHEEL
fishdata-1.9.dist-info/top_level.txt
fishdata-1.9.dist-info/RECORD
