Metadata-Version: 2.1
Name: fishdata
Version: 1.9
Summary: A package for managing fish data
Author: Carl-Emil
Author-email: carlemilkrag@email.com
